README.md
setup.py
soundarya_sreedevi.egg-info/PKG-INFO
soundarya_sreedevi.egg-info/SOURCES.txt
soundarya_sreedevi.egg-info/dependency_links.txt
soundarya_sreedevi.egg-info/top_level.txt
soundarya_sreedevi_modules/__init__.py
soundarya_sreedevi_modules/fatima.py
soundarya_sreedevi_modules/pallavi.py
soundarya_sreedevi_modules/shaan.py
soundarya_sreedevi_modules/srinivas.py
soundarya_sreedevi_modules/vishu.py