Metadata-Version: 2.1
Name: soundarya_sreedevi
Version: 0.1.0
Summary: A brief description of your package
Home-page: https://github.com/your-username/your-package
Author: Your Name
Author-email: your.email@example.com
Classifier: Programming Language :: Python :: 3
Classifier: License :: OSI Approved :: MIT License
Classifier: Operating System :: OS Independent
